bias_correction.py
bias_correction-0.4.dist-info/LICENSE
bias_correction-0.4.dist-info/METADATA
bias_correction-0.4.dist-info/WHEEL
bias_correction-0.4.dist-info/top_level.txt
bias_correction-0.4.dist-info/RECORD
