Metadata-Version: 2.1
Name: bias-correction
Version: 0.4
Summary: python library for bias_correction
Home-page: https://github.com/pankajkarman/bias_correction
Author: Pankaj Kumar
Author-email: pankaj.kmr1990@gmail.com
License: MIT
Platform: UNKNOWN
Requires-Python: >=3.6
Requires-Dist: numpy
Requires-Dist: scipy
Requires-Dist: pandas
Requires-Dist: statsmodels
Requires-Dist: xarray
